ekko_cli/__init__.py
ekko_cli/main.py
ekko_cli/utils.py
ekko_cli/dto/__init__.py
ekko_cli/dto/day_dto.py
ekko_cli/dto/entry_dto.py
ekko_cli/dto/journal_dto.py
ekko_cli/dto/label_dto.py
ekko_cli/scripts/__init__.py
ekko_cli/scripts/auth.py
ekko_cli/scripts/ekko.py
ekko_cli/scripts/labels.py
ekko_cli/utils/__init__.py
ekko_cli/utils/config_utils.py
ekko_cli/utils/database_utils.py
ekko_cli/utils/ekko_utils.py
ekko_cli/utils/label_utils.py
ekko_cli/utils/pocketbase_utils.py
ekko_cli/utils/session_utils.py
ekko_cli/utils/singleton_utils.py
ekko_cli-1.0.1.dist-info/entry_points.txt
ekko_cli-1.0.1.dist-info/licenses/LICENSE
ekko_cli-1.0.1.dist-info/WHEEL
ekko_cli-1.0.1.dist-info/METADATA
ekko_cli-1.0.1.dist-info/RECORD
