Metadata-Version: 2.4
Name: ekko-cli
Version: 1.0.1
Summary: Ekko by Zykkl
Author-email: Alex Carvalho <alex@zykkl.dev>
Requires-Python: >=3.11
License-Expression: MIT
License-File: LICENSE
Requires-Dist: click>=8.1
Requires-Dist: platformdirs
Requires-Dist: pocketbase
Requires-Dist: InquirerPy
Requires-Dist: rich
